[
  {
    "name": "antelope-canyon",
    "keywords": "canyon, red",
    "url": "images/search/antelope-canyon.jpg"
  },
  {
    "name": "aurora",
    "keywords": "aurora, landscape, atmospheric",
    "url": "images/search/aurora.jpg"
  },
  {
    "name": "autumn-leaves",
    "keywords": "autumn, leaves, wood",
    "url": "images/search/autumn-leaves.jpg"
  },
  {
    "name": "bandon-face-rock",
    "keywords": "beach, sunset",
    "url": "images/search/bandon-face-rock.jpg"
  },
  {
    "name": "big-city-life",
    "keywords": "city, night, dark",
    "url": "images/search/big-city-life.jpg"
  },
  {
    "name": "city-park",
    "keywords": "city, skyline, park",
    "url": "images/search/city-park.jpg"
  },
  {
    "name": "dragon-painting",
    "keywords": "dragon, dark, fire",
    "url": "images/search/dragon-painting.jpg"
  },
  {
    "name": "leeds-castle-grounds",
    "keywords": "landscape, lake, reflection, trees",
    "url": "images/search/leeds-castle-grounds.jpg"
  },
  {
    "name": "light-and-death",
    "keywords": "sci-fi, space, planet, moon, fire, future",
    "url": "images/search/light-and-death.jpg"
  },
  {
    "name": "lusitania-eclipse",
    "keywords": "planet, eclipse, sunset",
    "url": "images/search/lusitania-eclipse.jpg"
  },
  {
    "name": "moss",
    "keywords": "nature, moss, plant",
    "url": "images/search/moss.jpg"
  },
  {
    "name": "nature-illuminating-lotus",
    "keywords": "fantasy, lotus, sunset",
    "url": "images/search/nature-illuminating-lotus.jpg"
  },
  {
    "name": "ravine",
    "keywords": "nature, landscape, fantasy, tree",
    "url": "images/search/ravine.jpg"
  },
  {
    "name": "space-ship-transporter",
    "keywords": "sci-fi, spaceship, hangar, future",
    "url": "images/search/space-ship-transporter.jpg"
  },
  {
    "name": "streets-rain-cars-urban-buildings",
    "keywords": "city, street, rain, reflection",
    "url": "images/search/streets-rain-cars-urban-buildings.jpg"
  },
  {
    "name": "sunset-in-tairua",
    "keywords": "sunset, sea, nature, landscape",
    "url": "images/search/sunset-in-tairua.jpg"
  },
  {
    "name": "the-last-glow",
    "keywords": "sea, beach, sunset, stones",
    "url": "images/search/the-last-glow.jpg"
  },
  {
    "name": "winter-of-the-future",
    "keywords": "winter, moon, landscape, snow",
    "url": "images/search/winter-of-the-future.jpg"
  }
]